{
  "generatedAt": "2026-06-14T15:51:03.625Z",
  "weekRangeStart": "2026-06-15",
  "weekRangeEnd": "2026-06-29",
  "events": [
    {
      "date": "2026-06-17",
      "category": "other",
      "name": "미국 FOMC 금리 결정 (한국시간 6/18 새벽)",
      "importance": 4,
      "description": "미국 연방공개시장위원회(FOMC) 6월 회의(6/16~17, 미국시간) 결과 발표. 점도표(dot plot) 및 경제전망(SEP) 포함. 한국 금리·환율·증시에 직접 영향. 한국시간 기준 6월 18일(목) 새벽 3시경 발표.",
      "source": "federalreserve.gov / tmsstory.co.kr"
    },
    {
      "date": "2026-06-19",
      "category": "futures_expiry",
      "name": "KOSPI200 선물·옵션 분기 만기일",
      "importance": 2,
      "description": "6월 셋째 금요일로 KOSPI200 주가지수 선물·옵션 분기 만기일(쿼드러플위칭데이). 주식·선물·옵션·ETF 동시 만기로 변동성 확대 가능성. KRX 정기 일정 기준.",
      "source": "krx.co.kr"
    },
    {
      "date": "2026-06-23",
      "category": "other",
      "name": "한국은행 소비자심리지수(CCSI) 발표",
      "importance": 2,
      "description": "한국은행이 매월 말 발표하는 소비자동향조사(소비자심리지수). 6월 23일(화) 발표 예정. 가계의 경기 및 소비 심리를 반영하는 선행 지표.",
      "source": "month2k.com / bok.or.kr"
    },
    {
      "date": "2026-06-25",
      "category": "bok_mpb",
      "name": "한국은행 금융통화위원회 금융안정회의",
      "importance": 3,
      "description": "2026년 6월 금융통화위원회 금융안정회의(금융안정 상황 점검 회의). 정확한 날짜는 한국은행 공식 첨부파일 기준 미확인(추정 일정). 의사록은 7월 10일(금) 앞당겨 공개 예정. 기준금리 결정 회의 아님.",
      "source": "bok.or.kr"
    },
    {
      "date": "2026-06-30",
      "category": "industrial",
      "name": "2026년 5월 산업활동동향 발표",
      "importance": 3,
      "description": "국가데이터처(구 통계청)가 발표하는 5월 산업활동동향. 광공업 생산, 소매판매, 설비투자 등 포함. 6월 주요통계 공표일정에 공식 확인된 일정.",
      "source": "mods.go.kr"
    }
  ]
}
